CHANGELOG.md
LICENSE
MANIFEST.in
Makefile
README.md
setup.cfg
setup.py
tox.ini
tests/test_clear_view.py
tests/test_flags_set_view.py
tests/test_list_view.py
tests/test_sender.py
tests/test_stats_collector.py
wc_django_notifications.egg-info/PKG-INFO
wc_django_notifications.egg-info/SOURCES.txt
wc_django_notifications.egg-info/dependency_links.txt
wc_django_notifications.egg-info/requires.txt
wc_django_notifications.egg-info/top_level.txt
wcd_notifications/__init__.py
wcd_notifications/admin.py
wcd_notifications/apps.py
wcd_notifications/compat.py
wcd_notifications/conf.py
wcd_notifications/exceptions.py
wcd_notifications/signals.py
wcd_notifications/subscriptions.py
wcd_notifications/utils.py
wcd_notifications/contrib/__init__.py
wcd_notifications/contrib/drf/__init__.py
wcd_notifications/contrib/drf/apps.py
wcd_notifications/contrib/drf/filters.py
wcd_notifications/contrib/drf/serializers.py
wcd_notifications/contrib/drf/views.py
wcd_notifications/locale/af/LC_MESSAGES/django.mo
wcd_notifications/locale/af/LC_MESSAGES/django.po
wcd_notifications/locale/ar/LC_MESSAGES/django.mo
wcd_notifications/locale/ar/LC_MESSAGES/django.po
wcd_notifications/locale/ast/LC_MESSAGES/django.mo
wcd_notifications/locale/ast/LC_MESSAGES/django.po
wcd_notifications/locale/az/LC_MESSAGES/django.mo
wcd_notifications/locale/az/LC_MESSAGES/django.po
wcd_notifications/locale/be/LC_MESSAGES/django.mo
wcd_notifications/locale/be/LC_MESSAGES/django.po
wcd_notifications/locale/bg/LC_MESSAGES/django.mo
wcd_notifications/locale/bg/LC_MESSAGES/django.po
wcd_notifications/locale/bn/LC_MESSAGES/django.mo
wcd_notifications/locale/bn/LC_MESSAGES/django.po
wcd_notifications/locale/br/LC_MESSAGES/django.mo
wcd_notifications/locale/br/LC_MESSAGES/django.po
wcd_notifications/locale/bs/LC_MESSAGES/django.mo
wcd_notifications/locale/bs/LC_MESSAGES/django.po
wcd_notifications/locale/ca/LC_MESSAGES/django.mo
wcd_notifications/locale/ca/LC_MESSAGES/django.po
wcd_notifications/locale/cs/LC_MESSAGES/django.mo
wcd_notifications/locale/cs/LC_MESSAGES/django.po
wcd_notifications/locale/cy/LC_MESSAGES/django.mo
wcd_notifications/locale/cy/LC_MESSAGES/django.po
wcd_notifications/locale/da/LC_MESSAGES/django.mo
