Metadata-Version: 2.4
Name: wc-django-notifications
Version: 0.3.2
Summary: Modular notifications system for your django applications.
Author: WebCase
Author-email: info@webcase.studio
License: MIT License
Classifier: Development Status :: 2 - Pre-Alpha
Classifier: Programming Language :: Python :: 3
Classifier: Intended Audience :: Developers
Classifier: Topic :: Utilities
Classifier: License :: OSI Approved :: MIT License
Classifier: Operating System :: OS Independent
Requires-Python: >=3.6
License-File: LICENSE
Requires-Dist: px-settings<0.2.0,>=0.1.3
Requires-Dist: px-pipeline<0.2.0,>=0.1.2
Requires-Dist: django-prettyjson<0.5.0,>=0.4.1
Provides-Extra: dev
Requires-Dist: pytest<7.0,>=6.0; extra == "dev"
Requires-Dist: pytest-watch<5.0,>=4.2; extra == "dev"
Requires-Dist: pytest-django<5.0,>=4.3; extra == "dev"
Requires-Dist: coverage==6.4.2; extra == "dev"
Requires-Dist: django-environ==0.4.5; extra == "dev"
Requires-Dist: django-stubs; extra == "dev"
Requires-Dist: django<4,>=2.2; extra == "dev"
Requires-Dist: twine; extra == "dev"
Provides-Extra: drf
Requires-Dist: wc-shortcodes<0.2.0,>=0.1.0; extra == "drf"
Requires-Dist: django-filter<23,>=21.1; extra == "drf"
Requires-Dist: djangorestframework<4.0.0,>=3.0.0; extra == "drf"
Dynamic: author
Dynamic: author-email
Dynamic: classifier
Dynamic: description
Dynamic: description-content-type
Dynamic: license
Dynamic: license-file
Dynamic: provides-extra
Dynamic: requires-dist
Dynamic: requires-python
Dynamic: summary
